src/FileSelector.py
src/__init__.py
File_Selector_Input-0.1.dist-info/LICENCE
File_Selector_Input-0.1.dist-info/METADATA
File_Selector_Input-0.1.dist-info/WHEEL
File_Selector_Input-0.1.dist-info/top_level.txt
File_Selector_Input-0.1.dist-info/RECORD
